Metadata-Version: 2.1
Name: py_order_utils
Version: 0.3.1
Summary: Python utilities used to generate and sign orders from Polymarket's Exchange
Home-page: https://github.com/polymarket/python-order-utils
Author: Polymarket Engineering
Author-email: engineering@polymarket.com
Maintainer: Polymarket Engineering
Maintainer-email: engineering@polymarket.com
Project-URL: Bug Tracker, https://github.com/polymarket/python-order-utils
Classifier: Programming Language :: Python :: 3
Classifier: License :: OSI Approved :: MIT License
Classifier: Operating System :: OS Independent
Requires-Python: >=3.9.10
License-File: LICENSE
Requires-Dist: eth-utils >=4.1.1
Requires-Dist: eth-account >=0.13.0
Requires-Dist: poly-eip712-structs
Requires-Dist: pytest
